nchuchain/__init__.py
nchuchain/chains/__init__.py
nchuchain/chains/retrieval_qa.py
nchuchain/data_modules/__init__.py
nchuchain/data_modules/context_prefix_tree.py
nchuchain/llms/__init__.py
nchuchain/llms/chat_completions_llm.py
nchuchain/loaders/__init__.py
nchuchain/loaders/text_loader.py
nchuchain/models/__init__.py
nchuchain/models/base.py
nchuchain/models/generative_model.py
nchuchain/retrievers/__init__.py
nchuchain/retrievers/base.py
nchuchain/retrievers/pyserini_bm25.py
nchuchain/retrievers/rank_bm25.py
nchuchain/splitters/__init__.py
nchuchain/splitters/text_splitter.py
nchuchain/utils/__init__.py
nchuchain/utils/config.py
nchuchain/utils/data.py
nchuchain/utils/template.py
nchuchain-1.0.11.dist-info/LICENSE
nchuchain-1.0.11.dist-info/METADATA
nchuchain-1.0.11.dist-info/WHEEL
nchuchain-1.0.11.dist-info/top_level.txt
nchuchain-1.0.11.dist-info/RECORD
