Metadata-Version: 2.1
Name: nchuchain
Version: 1.0.11
Summary: A set of data tools in Python
Home-page: https://github.com/good22014040/nchuchain
Download-URL: https://pypi.org/project/nchuchain/
Author: WenChuan Hsu
Author-email: wenchuan19991111@gmail.com
License: MIT
Classifier: Programming Language :: Python :: 3.8
Classifier: Programming Language :: Python :: 3.9
Classifier: Programming Language :: Python :: 3.10
Requires-Python: >=3.8
License-File: LICENSE
Requires-Dist: torch
Requires-Dist: torchaudio
Requires-Dist: torchvision
Requires-Dist: bitsandbytes >=0.41.1
Requires-Dist: transformers >=4.36.0
Requires-Dist: accelerate >=0.21.0
Requires-Dist: scipy >=1.11.4
Provides-Extra: dev
Requires-Dist: pyserini ==0.22.1 ; extra == 'dev'
Requires-Dist: faiss-cpu ==1.7.4 ; extra == 'dev'
Requires-Dist: rank-bm25 ; extra == 'dev'
